cd2datamanager/__init__.py
cd2datamanager/__main__.py
cd2datamanager/constants.py
cd2datamanager/dap_client.py
cd2datamanager/main.py
cd2datamanager/schema_generator.py
cd2datamanager/schema_writer.py
cd2datamanager/semaphore_control.py
cd2datamanager/settings.py
cd2datamanager/tsv_generator.py
cd2datamanager/workspace.py
cd2datamanager-1.2.0.dist-info/LICENSE
cd2datamanager-1.2.0.dist-info/METADATA
cd2datamanager-1.2.0.dist-info/WHEEL
cd2datamanager-1.2.0.dist-info/entry_points.txt
cd2datamanager-1.2.0.dist-info/top_level.txt
cd2datamanager-1.2.0.dist-info/RECORD
