Metadata-Version: 2.1
Name: cd2datamanager
Version: 1.2.0
Summary: Canvas Data 2 Data Manager
Home-page: https://github.com/tiberhealth/CanvasData2
Author: Tiber Health Innovations
Author-email: tiber-tools@tiberhealth.com
License-File: LICENSE
Requires-Dist: asyncio
Requires-Dist: instructure-dap-client
Requires-Dist: tqdm
Requires-Dist: PyYaml
Requires-Dist: typer
Requires-Dist: tiberlogger
